event_triggering/__init__.py
event_triggering/custom_pubsub_sensor.py
event_triggering/pubsub_publisher.py
event_triggering/shared_topic_pubsub_sensor.py
airflow_extension_triggers-0.79.dist-info/LICENSE
airflow_extension_triggers-0.79.dist-info/METADATA
airflow_extension_triggers-0.79.dist-info/WHEEL
airflow_extension_triggers-0.79.dist-info/top_level.txt
airflow_extension_triggers-0.79.dist-info/RECORD
