Metadata-Version: 2.1
Name: airflow-extension-triggers
Version: 0.79
Summary: Package to expand Airflow for triggering events.
Home-page: https://github.com/nytm/airflow_extensions/event_triggering
Author: Sarah Duncan
Author-email: sarah.duncan@nytimes.com
License: Apache License 2.0
Platform: UNKNOWN
Requires-Dist: tzlocal (<2.0.0.0,>=1.5.0.0)
